noamath/__init__.py
noamath/geometry.py
noamath/main.py
noamath/rands.py
noamath-0.0.8.1.dist-info/licenses/LICENSE
noamath-0.0.8.1.dist-info/METADATA
noamath-0.0.8.1.dist-info/WHEEL
noamath-0.0.8.1.dist-info/top_level.txt
noamath-0.0.8.1.dist-info/RECORD
