Metadata-Version: 2.4
Name: noamath
Version: 0.0.8.1
Summary: A Math Library
Author: Noah Edward Holmén
Author-email: GanonBlasterTheGrey@gmail.com
License: Source Available License (see LICENSE file)
Classifier: Programming Language :: Python :: 3
Classifier: License :: Free To Use But Restricted
Classifier: Operating System :: OS Independent
Requires-Python: >=3.6
License-File: LICENSE
Requires-Dist: numpy
Dynamic: author
Dynamic: author-email
Dynamic: classifier
Dynamic: description
Dynamic: description-content-type
Dynamic: license
Dynamic: license-file
Dynamic: requires-dist
Dynamic: requires-python
Dynamic: summary
